fast_flow/__init__.py
fast_flow/help.py
fast_flow/version.py
fast_flow/v1/__init__.py
fast_flow/v1/config_exceptions.py
fast_flow/v1/dict_config.py
fast_flow/v1/yaml_config.py
fast_flow-0.6.1.dist-info/LICENSE
fast_flow-0.6.1.dist-info/METADATA
fast_flow-0.6.1.dist-info/WHEEL
fast_flow-0.6.1.dist-info/top_level.txt
fast_flow-0.6.1.dist-info/RECORD
