Metadata-Version: 2.1
Name: fast-flow
Version: 0.6.1
Summary: YAML-based analysis flow description language
Home-page: https://github.com/fast-hep/fast-flow
Author: Ben Krikler
Author-email: fast-hep@cern.ch
License: UNKNOWN
Platform: UNKNOWN
Classifier: Programming Language :: Python :: 2
Classifier: Programming Language :: Python :: 3
Classifier: License :: OSI Approved :: MIT License
Classifier: Operating System :: OS Independent
Classifier: Topic :: Software Development :: Libraries :: Python Modules
Classifier: Topic :: Utilities
Classifier: Development Status :: 3 - Alpha
Requires-Dist: six
Requires-Dist: pyyaml
